ploteries/__init__.py
ploteries/_table_handler_cli_interface.py
ploteries/base_handlers.py
ploteries/ndarray_data_handlers.py
ploteries/serializable_data_handler.py
ploteries/train_manager_visualizations.py
ploteries/writer.py
ploteries/_bin_helpers/__init__.py
ploteries/_bin_helpers/launch.py
ploteries/_bin_helpers/main.py
ploteries/_bin_helpers/mock_generator.py
ploteries/_bin_helpers/utils.py
ploteries/cli_interface/__init__.py
ploteries/cli_interface/abstract_hook.py
ploteries/cli_interface/cli_interface.py
ploteries/cli_interface/figure_handler_hook.py
ploteries/cli_interface/table_handler_hook.py
ploteries/data_store/__init__.py
ploteries/data_store/_legacy_type_deserializers.py
ploteries/data_store/data_store.py
ploteries/figure_handler/__init__.py
ploteries/figure_handler/figure_handler.py
ploteries/figure_handler/helpers.py
ploteries/figure_handler/scalars_figure_handler.py
ploteries/figure_handler/table_handler.py
ploteries-0.1.2.data/scripts/ploteries
ploteries-0.1.2.dist-info/LICENSE
ploteries-0.1.2.dist-info/METADATA
ploteries-0.1.2.dist-info/WHEEL
ploteries-0.1.2.dist-info/top_level.txt
ploteries-0.1.2.dist-info/RECORD
