Metadata-Version: 2.1
Name: ploteries
Version: 0.1.2
Summary: Plotting for ML training
Home-page: https://github.com/zepedaj/soleil
Author: Joaquin Zepeda
Keywords: plots,tensorboard,machine learning,training
License-File: LICENSE
Requires-Dist: pytest
Requires-Dist: sphinx
Requires-Dist: enum-tools
Requires-Dist: numpy
Requires-Dist: sqlalchemy ==1.4.46
Requires-Dist: climax
Requires-Dist: dash
Requires-Dist: dash-daq
Requires-Dist: gunicorn
Requires-Dist: jztools >=0.1.5
Requires-Dist: pandas
Requires-Dist: rich
